setup.py
lsc_distributions/Binomialdistribution.py
lsc_distributions/Gaussiandistribution.py
lsc_distributions/Generaldistribution.py
lsc_distributions/__init__.py
lsc_distributions.egg-info/PKG-INFO
lsc_distributions.egg-info/SOURCES.txt
lsc_distributions.egg-info/dependency_links.txt
lsc_distributions.egg-info/not-zip-safe
lsc_distributions.egg-info/top_level.txt