Metadata-Version: 1.0
Name: lsc-distributions
Version: 0.1
Summary: Gaussian and Binomial distributions
Home-page: UNKNOWN
Author: Lucian Stefan Craciun
Author-email: lucyans_c@yahoo.com
License: UNKNOWN
Platform: UNKNOWN
